behringer_mixer/__init__.py
behringer_mixer/errors.py
behringer_mixer/mappings.py
behringer_mixer/mixer_api.py
behringer_mixer/mixer_base.py
behringer_mixer/mixer_osc.py
behringer_mixer/mixer_types.py
behringer_mixer/mixers/mixer_type_base.py
behringer_mixer/mixers/mixer_type_wing.py
behringer_mixer/mixers/mixer_type_x32.py
behringer_mixer/mixers/mixer_type_xair.py
behringer_mixer/mixers/mixer_type_xr12.py
behringer_mixer/mixers/mixer_type_xr16.py
behringer_mixer/mixers/mixer_type_xr18.py
behringer_mixer/mixers/mixer_type_xseries_base.py
behringer_mixer/utils.py
behringer_mixer-0.4.12.dist-info/LICENSE
behringer_mixer-0.4.12.dist-info/METADATA
behringer_mixer-0.4.12.dist-info/WHEEL
behringer_mixer-0.4.12.dist-info/RECORD
