Metadata-Version: 2.1
Name: behringer_mixer
Version: 0.4.12
Summary: Module to get basic information from Behringer digital mixers eg X32/XAir etc.
Home-page: https://github.com/wrodie/behringer-mixer
License: MIT
Author: wrodie
Author-email: warren@rodie.net
Requires-Python: >=3.10,<4.0
Classifier: License :: OSI Approved :: MIT License
Classifier: Programming Language :: Python :: 3
Classifier: Programming Language :: Python :: 3.10
Classifier: Programming Language :: Python :: 3.11
Classifier: Programming Language :: Python :: 3.12
Requires-Dist: python-osc (>=1.8.0,<2.0.0)
Project-URL: Repository, https://github.com/wrodie/behringer-mixer
